intelium/__init__.py
intelium/browser/__init__.py
intelium/browser/automation.py
intelium/core/__init__.py
intelium/core/automation.py
intelium/desktop/__init__.py
intelium/desktop/automation.py
intelium-0.1.dist-info/licenses/LICENSE
intelium-0.1.dist-info/METADATA
intelium-0.1.dist-info/WHEEL
intelium-0.1.dist-info/top_level.txt
intelium-0.1.dist-info/RECORD
